{
    "name": "Học viện Báo chí và Tuyên truyền",
    "id": "HBT",
    "region": "Hà Nội",
    "contact_details": {
        "location": "36 Xuân Thủy - Cầu Giấy - Hà Nội",
        "phone": [
            "0243.754.6963"
        ],
        "website": "http://tuyensinhajc.edu.vn/",
        "email": [
            "hbt.tuyensinh@gmail.com"
        ]
    },
    "admission_details": {
        "year": 2024,
        "admission_target": 2400,
        "methods": [
            "Xét học bạ",
            "Xét tuyển kết hợp chứng chỉ quốc tế",
            "Xét tuyển căn cứ kết quả thi tốt nghiệp THPT"
        ]
    }
}